gget_mcp/__init__.py
gget_mcp/server.py
gget_mcp/server_ext.py
gget_mcp-0.3.1.dist-info/METADATA
gget_mcp-0.3.1.dist-info/WHEEL
gget_mcp-0.3.1.dist-info/entry_points.txt
gget_mcp-0.3.1.dist-info/licenses/LICENSE
gget_mcp-0.3.1.dist-info/RECORD
