Metadata-Version: 2.4
Name: gget-mcp
Version: 0.3.1
Summary: MCP server for gget bioinformatics library
Author-email: antonkulaga <antonkulaga@gmail.com>, Newton Winter <isoutthere@gmail.com>
License-File: LICENSE
Requires-Python: >=3.10
Requires-Dist: biopython>=1.84
Requires-Dist: eliot>=1.17.5
Requires-Dist: fastapi>=0.115.12
Requires-Dist: fastmcp>=2.7.0
Requires-Dist: gget>=0.29.1
Requires-Dist: openmm>=8.3.0
Requires-Dist: pandas>=2.0.0
Requires-Dist: py3dmol>=2.5.0
Requires-Dist: pycomfort>=0.0.18
Requires-Dist: simtk>=0.1.0
Requires-Dist: typer>=0.16.0
